sentry_sso_google/__init__.py
sentry_sso_google/models.py
sentry_sso_google/provider.py
sentry_sso_google-1.2.dist-info/DESCRIPTION.rst
sentry_sso_google-1.2.dist-info/METADATA
sentry_sso_google-1.2.dist-info/RECORD
sentry_sso_google-1.2.dist-info/WHEEL
sentry_sso_google-1.2.dist-info/metadata.json
sentry_sso_google-1.2.dist-info/pbr.json
sentry_sso_google-1.2.dist-info/top_level.txt
