Metadata-Version: 2.0
Name: sentry-sso-google
Version: 1.2
Summary: Google SSO support for Sentry
Home-page: https://github.com/educreations/sentry-sso-google
Author: Educreations Engineering
Author-email: engineering@educreations.com
License: MIT
Platform: UNKNOWN
Requires-Dist: sentry (>=7.5)
